{
    "geocoded_waypoints": [
        {
            "geocoder_status": "OK",
            "place_id": "ChIJAw83lEL7ykARHPpBrKCeNr0",
            "types": [
                "establishment",
                "point_of_interest",
                "transit_station"
            ]
        },
        {
            "geocoder_status": "OK",
            "place_id": "ChIJo1ylNEz7ykAR_ewF4bKnrnY",
            "types": [
                "establishment",
                "point_of_interest",
                "transit_station"
            ]
        }
    ],
    "routes": [
        {
            "bounds": {
                "south": 47.16816,
                "west": 27.5374,
                "north": 47.173320000000004,
                "east": 27.558400000000002
            },
            "copyrights": "Map data \u00a92024",
            "legs": [
                {
                    "distance": {
                        "text": "2,0 km",
                        "value": 2033
                    },
                    "duration": {
                        "text": "6 min",
                        "value": 368
                    },
                    "duration_in_traffic": {
                        "text": "4 min",
                        "value": 257
                    },
                    "end_address": "Canta, Ia\u0219i, Rom\u00e2nia",
                    "end_location": {
                        "lat": 47.1724089,
                        "lng": 27.537439
                    },
                    "start_address": "Piata Sf. Anton de Padova, Ia\u0219i, Rom\u00e2nia",
                    "start_location": {
                        "lat": 47.168156,
                        "lng": 27.558396
                    },
                    "steps": [
                        {
                            "distance": {
                                "text": "0,7 km",
                                "value": 683
                            },
                            "duration": {
                                "text": "2 min",
                                "value": 108
                            },
                            "end_location": {
                                "lat": 47.1694231,
                                "lng": 27.5500283
                            },
                            "polyline": {
                                "points": "_p{~G_oegD]`@I?C@EBg@j@?@A?A??@A?A@?@A??@A??@A@?@A@A@?@A@?@?@AB?@?@A@?@?B?@?BEDCBABADENADAB?B?BGPCJo@lCMl@Ij@E`@A`@C\\APAn@@n@?rA?^?d@AX?R?nAArB?RApCEjHCtC"
                            },
                            "start_location": {
                                "lat": 47.168156,
                                "lng": 27.558396
                            },
                            "travel_mode": "DRIVING",
                            "encoded_lat_lngs": "_p{~G_oegD]`@I?C@EBg@j@?@A?A??@A?A@?@A??@A??@A@?@A@A@?@A@?@?@AB?@?@A@?@?B?@?BEDCBABADENADAB?B?BGPCJo@lCMl@Ij@E`@A`@C\\APAn@@n@?rA?^?d@AX?R?nAArB?RApCEjHCtC",
                            "path": [
                                {
                                    "lat": 47.16816,
                                    "lng": 27.558400000000002
                                },
                                {
                                    "lat": 47.168310000000005,
                                    "lng": 27.558230000000002
                                },
                                {
                                    "lat": 47.16836000000001,
                                    "lng": 27.558230000000002
                                },
                                {
                                    "lat": 47.168380000000006,
                                    "lng": 27.558220000000002
                                },
                                {
                                    "lat": 47.16841,
                                    "lng": 27.558200000000003
                                },
                                {
                                    "lat": 47.16861,
                                    "lng": 27.55798
                                },
                                {
                                    "lat": 47.16861,
                                    "lng": 27.55797
                                },
                                {
                                    "lat": 47.168620000000004,
                                    "lng": 27.55797
                                },
                                {
                                    "lat": 47.16863000000001,
                                    "lng": 27.55797
                                },
                                {
                                    "lat": 47.16863000000001,
                                    "lng": 27.55796
                                },
                                {
                                    "lat": 47.16864,
                                    "lng": 27.55796
                                },
                                {
                                    "lat": 47.16865000000001,
                                    "lng": 27.55795
                                },
                                {
                                    "lat": 47.16865000000001,
                                    "lng": 27.557940000000002
                                },
                                {
                                    "lat": 47.16866,
                                    "lng": 27.557940000000002
                                },
                                {
                                    "lat": 47.16866,
                                    "lng": 27.557930000000002
                                },
                                {
                                    "lat": 47.168670000000006,
                                    "lng": 27.557930000000002
                                },
                                {
                                    "lat": 47.168670000000006,
                                    "lng": 27.557920000000003
                                },
                                {
                                    "lat": 47.16868,
                                    "lng": 27.557910000000003
                                },
                                {
                                    "lat": 47.16868,
                                    "lng": 27.557900000000004
                                },
                                {
                                    "lat": 47.168690000000005,
                                    "lng": 27.557890000000004
                                },
                                {
                                    "lat": 47.1687,
                                    "lng": 27.55788
                                },
                                {
                                    "lat": 47.1687,
                                    "lng": 27.55787
                                },
                                {
                                    "lat": 47.168710000000004,
                                    "lng": 27.55786
                                },
                                {
                                    "lat": 47.168710000000004,
                                    "lng": 27.557850000000002
                                },
                                {
                                    "lat": 47.168710000000004,
                                    "lng": 27.557840000000002
                                },
                                {
                                    "lat": 47.16872,
                                    "lng": 27.557820000000003
                                },
                                {
                                    "lat": 47.16872,
                                    "lng": 27.557810000000003
                                },
                                {
                                    "lat": 47.16872,
                                    "lng": 27.557800000000004
                                },
                                {
                                    "lat": 47.168730000000004,
                                    "lng": 27.55779
                                },
                                {
                                    "lat": 47.168730000000004,
                                    "lng": 27.55778
                                },
                                {
                                    "lat": 47.168730000000004,
                                    "lng": 27.557760000000002
                                },
                                {
                                    "lat": 47.168730000000004,
                                    "lng": 27.557750000000002
                                },
                                {
                                    "lat": 47.168730000000004,
                                    "lng": 27.557730000000003
                                },
                                {
                                    "lat": 47.168760000000006,
                                    "lng": 27.5577
                                },
                                {
                                    "lat": 47.168780000000005,
                                    "lng": 27.55768
                                },
                                {
                                    "lat": 47.16879,
                                    "lng": 27.557660000000002
                                },
                                {
                                    "lat": 47.168800000000005,
                                    "lng": 27.557630000000003
                                },
                                {
                                    "lat": 47.16883000000001,
                                    "lng": 27.557550000000003
                                },
                                {
                                    "lat": 47.16884,
                                    "lng": 27.557520000000004
                                },
                                {
                                    "lat": 47.168850000000006,
                                    "lng": 27.5575
                                },
                                {
                                    "lat": 47.168850000000006,
                                    "lng": 27.55748
                                },
                                {
                                    "lat": 47.168850000000006,
                                    "lng": 27.557460000000003
                                },
                                {
                                    "lat": 47.168890000000005,
                                    "lng": 27.557370000000002
                                },
                                {
                                    "lat": 47.168910000000004,
                                    "lng": 27.55731
                                },
                                {
                                    "lat": 47.16915,
                                    "lng": 27.556600000000003
                                },
                                {
                                    "lat": 47.16922,
                                    "lng": 27.55637
                                },
                                {
                                    "lat": 47.169270000000004,
                                    "lng": 27.556150000000002
                                },
                                {
                                    "lat": 47.16930000000001,
                                    "lng": 27.55598
                                },
                                {
                                    "lat": 47.16931,
                                    "lng": 27.55581
                                },
                                {
                                    "lat": 47.16933,
                                    "lng": 27.555660000000003
                                },
                                {
                                    "lat": 47.169340000000005,
                                    "lng": 27.555570000000003
                                },
                                {
                                    "lat": 47.16935,
                                    "lng": 27.55533
                                },
                                {
                                    "lat": 47.169340000000005,
                                    "lng": 27.555090000000003
                                },
                                {
                                    "lat": 47.169340000000005,
                                    "lng": 27.55467
                                },
                                {
                                    "lat": 47.169340000000005,
                                    "lng": 27.55451
                                },
                                {
                                    "lat": 47.169340000000005,
                                    "lng": 27.55432
                                },
                                {
                                    "lat": 47.16935,
                                    "lng": 27.554190000000002
                                },
                                {
                                    "lat": 47.16935,
                                    "lng": 27.554090000000002
                                },
                                {
                                    "lat": 47.16935,
                                    "lng": 27.553690000000003
                                },
                                {
                                    "lat": 47.169360000000005,
                                    "lng": 27.553110000000004
                                },
                                {
                                    "lat": 47.169360000000005,
                                    "lng": 27.553010000000004
                                },
                                {
                                    "lat": 47.16937,
                                    "lng": 27.552280000000003
                                },
                                {
                                    "lat": 47.1694,
                                    "lng": 27.550780000000003
                                },
                                {
                                    "lat": 47.16942,
                                    "lng": 27.550030000000003
                                }
                            ],
                            "lat_lngs": [
                                {
                                    "lat": 47.16816,
                                    "lng": 27.558400000000002
                                },
                                {
                                    "lat": 47.168310000000005,
                                    "lng": 27.558230000000002
                                },
                                {
                                    "lat": 47.16836000000001,
                                    "lng": 27.558230000000002
                                },
                                {
                                    "lat": 47.168380000000006,
                                    "lng": 27.558220000000002
                                },
                                {
                                    "lat": 47.16841,
                                    "lng": 27.558200000000003
                                },
                                {
                                    "lat": 47.16861,
                                    "lng": 27.55798
                                },
                                {
                                    "lat": 47.16861,
                                    "lng": 27.55797
                                },
                                {
                                    "lat": 47.168620000000004,
                                    "lng": 27.55797
                                },
                                {
                                    "lat": 47.16863000000001,
                                    "lng": 27.55797
                                },
                                {
                                    "lat": 47.16863000000001,
                                    "lng": 27.55796
                                },
                                {
                                    "lat": 47.16864,
                                    "lng": 27.55796
                                },
                                {
                                    "lat": 47.16865000000001,
                                    "lng": 27.55795
                                },
                                {
                                    "lat": 47.16865000000001,
                                    "lng": 27.557940000000002
                                },
                                {
                                    "lat": 47.16866,
                                    "lng": 27.557940000000002
                                },
                                {
                                    "lat": 47.16866,
                                    "lng": 27.557930000000002
                                },
                                {
                                    "lat": 47.168670000000006,
                                    "lng": 27.557930000000002
                                },
                                {
                                    "lat": 47.168670000000006,
                                    "lng": 27.557920000000003
                                },
                                {
                                    "lat": 47.16868,
                                    "lng": 27.557910000000003
                                },
                                {
                                    "lat": 47.16868,
                                    "lng": 27.557900000000004
                                },
                                {
                                    "lat": 47.168690000000005,
                                    "lng": 27.557890000000004
                                },
                                {
                                    "lat": 47.1687,
                                    "lng": 27.55788
                                },
                                {
                                    "lat": 47.1687,
                                    "lng": 27.55787
                                },
                                {
                                    "lat": 47.168710000000004,
                                    "lng": 27.55786
                                },
                                {
                                    "lat": 47.168710000000004,
                                    "lng": 27.557850000000002
                                },
                                {
                                    "lat": 47.168710000000004,
                                    "lng": 27.557840000000002
                                },
                                {
                                    "lat": 47.16872,
                                    "lng": 27.557820000000003
                                },
                                {
                                    "lat": 47.16872,
                                    "lng": 27.557810000000003
                                },
                                {
                                    "lat": 47.16872,
                                    "lng": 27.557800000000004
                                },
                                {
                                    "lat": 47.168730000000004,
                                    "lng": 27.55779
                                },
                                {
                                    "lat": 47.168730000000004,
                                    "lng": 27.55778
                                },
                                {
                                    "lat": 47.168730000000004,
                                    "lng": 27.557760000000002
                                },
                                {
                                    "lat": 47.168730000000004,
                                    "lng": 27.557750000000002
                                },
                                {
                                    "lat": 47.168730000000004,
                                    "lng": 27.557730000000003
                                },
                                {
                                    "lat": 47.168760000000006,
                                    "lng": 27.5577
                                },
                                {
                                    "lat": 47.168780000000005,
                                    "lng": 27.55768
                                },
                                {
                                    "lat": 47.16879,
                                    "lng": 27.557660000000002
                                },
                                {
                                    "lat": 47.168800000000005,
                                    "lng": 27.557630000000003
                                },
                                {
                                    "lat": 47.16883000000001,
                                    "lng": 27.557550000000003
                                },
                                {
                                    "lat": 47.16884,
                                    "lng": 27.557520000000004
                                },
                                {
                                    "lat": 47.168850000000006,
                                    "lng": 27.5575
                                },
                                {
                                    "lat": 47.168850000000006,
                                    "lng": 27.55748
                                },
                                {
                                    "lat": 47.168850000000006,
                                    "lng": 27.557460000000003
                                },
                                {
                                    "lat": 47.168890000000005,
                                    "lng": 27.557370000000002
                                },
                                {
                                    "lat": 47.168910000000004,
                                    "lng": 27.55731
                                },
                                {
                                    "lat": 47.16915,
                                    "lng": 27.556600000000003
                                },
                                {
                                    "lat": 47.16922,
                                    "lng": 27.55637
                                },
                                {
                                    "lat": 47.169270000000004,
                                    "lng": 27.556150000000002
                                },
                                {
                                    "lat": 47.16930000000001,
                                    "lng": 27.55598
                                },
                                {
                                    "lat": 47.16931,
                                    "lng": 27.55581
                                },
                                {
                                    "lat": 47.16933,
                                    "lng": 27.555660000000003
                                },
                                {
                                    "lat": 47.169340000000005,
                                    "lng": 27.555570000000003
                                },
                                {
                                    "lat": 47.16935,
                                    "lng": 27.55533
                                },
                                {
                                    "lat": 47.169340000000005,
                                    "lng": 27.555090000000003
                                },
                                {
                                    "lat": 47.169340000000005,
                                    "lng": 27.55467
                                },
                                {
                                    "lat": 47.169340000000005,
                                    "lng": 27.55451
                                },
                                {
                                    "lat": 47.169340000000005,
                                    "lng": 27.55432
                                },
                                {
                                    "lat": 47.16935,
                                    "lng": 27.554190000000002
                                },
                                {
                                    "lat": 47.16935,
                                    "lng": 27.554090000000002
                                },
                                {
                                    "lat": 47.16935,
                                    "lng": 27.553690000000003
                                },
                                {
                                    "lat": 47.169360000000005,
                                    "lng": 27.553110000000004
                                },
                                {
                                    "lat": 47.169360000000005,
                                    "lng": 27.553010000000004
                                },
                                {
                                    "lat": 47.16937,
                                    "lng": 27.552280000000003
                                },
                                {
                                    "lat": 47.1694,
                                    "lng": 27.550780000000003
                                },
                                {
                                    "lat": 47.16942,
                                    "lng": 27.550030000000003
                                }
                            ],
                            "instructions": "Mergi spre <b>nord-vest</b> pe <b>\u0218oseaua Na\u021bional\u0103</b> c\u0103tre <b>Pasarela Pictor Octav B\u0103ncil\u0103</b><div style=\"font-size:0.9em\">Treci printr-un sens giratoriu</div>",
                            "maneuver": "",
                            "start_point": {
                                "lat": 47.168156,
                                "lng": 27.558396
                            },
                            "end_point": {
                                "lat": 47.1694231,
                                "lng": 27.5500283
                            }
                        },
                        {
                            "distance": {
                                "text": "0,1 km",
                                "value": 113
                            },
                            "duration": {
                                "text": "1 min",
                                "value": 16
                            },
                            "end_location": {
                                "lat": 47.170401,
                                "lng": 27.5497588
                            },
                            "maneuver": "turn-right",
                            "polyline": {
                                "points": "{w{~GuzcgDa@Cs@?M@I@aAh@SJ"
                            },
                            "start_location": {
                                "lat": 47.1694231,
                                "lng": 27.5500283
                            },
                            "travel_mode": "DRIVING",
                            "encoded_lat_lngs": "{w{~GuzcgDa@Cs@?M@I@aAh@SJ",
                            "path": [
                                {
                                    "lat": 47.16942,
                                    "lng": 27.550030000000003
                                },
                                {
                                    "lat": 47.16959000000001,
                                    "lng": 27.550050000000002
                                },
                                {
                                    "lat": 47.169850000000004,
                                    "lng": 27.550050000000002
                                },
                                {
                                    "lat": 47.169920000000005,
                                    "lng": 27.550040000000003
                                },
                                {
                                    "lat": 47.169970000000006,
                                    "lng": 27.550030000000003
                                },
                                {
                                    "lat": 47.170300000000005,
                                    "lng": 27.549820000000004
                                },
                                {
                                    "lat": 47.1704,
                                    "lng": 27.549760000000003
                                }
                            ],
                            "lat_lngs": [
                                {
                                    "lat": 47.16942,
                                    "lng": 27.550030000000003
                                },
                                {
                                    "lat": 47.16959000000001,
                                    "lng": 27.550050000000002
                                },
                                {
                                    "lat": 47.169850000000004,
                                    "lng": 27.550050000000002
                                },
                                {
                                    "lat": 47.169920000000005,
                                    "lng": 27.550040000000003
                                },
                                {
                                    "lat": 47.169970000000006,
                                    "lng": 27.550030000000003
                                },
                                {
                                    "lat": 47.170300000000005,
                                    "lng": 27.549820000000004
                                },
                                {
                                    "lat": 47.1704,
                                    "lng": 27.549760000000003
                                }
                            ],
                            "instructions": "Vireaz\u0103 <b>la dreapta</b>",
                            "start_point": {
                                "lat": 47.1694231,
                                "lng": 27.5500283
                            },
                            "end_point": {
                                "lat": 47.170401,
                                "lng": 27.5497588
                            }
                        },
                        {
                            "distance": {
                                "text": "0,4 km",
                                "value": 361
                            },
                            "duration": {
                                "text": "1 min",
                                "value": 56
                            },
                            "end_location": {
                                "lat": 47.1716746,
                                "lng": 27.5460916
                            },
                            "maneuver": "straight",
                            "polyline": {
                                "points": "_~{~G_ycgDuAz@KF}BvAGHEFABABADAF?bDAlAC`ACl@AJ?BA\\@hBB^"
                            },
                            "start_location": {
                                "lat": 47.170401,
                                "lng": 27.5497588
                            },
                            "travel_mode": "DRIVING",
                            "encoded_lat_lngs": "_~{~G_ycgDuAz@KF}BvAGHEFABABADAF?bDAlAC`ACl@AJ?BA\\@hBB^",
                            "path": [
                                {
                                    "lat": 47.1704,
                                    "lng": 27.549760000000003
                                },
                                {
                                    "lat": 47.17083,
                                    "lng": 27.549460000000003
                                },
                                {
                                    "lat": 47.17089000000001,
                                    "lng": 27.54942
                                },
                                {
                                    "lat": 47.17152,
                                    "lng": 27.548980000000004
                                },
                                {
                                    "lat": 47.17156000000001,
                                    "lng": 27.548930000000002
                                },
                                {
                                    "lat": 47.17159,
                                    "lng": 27.548890000000004
                                },
                                {
                                    "lat": 47.171600000000005,
                                    "lng": 27.54887
                                },
                                {
                                    "lat": 47.17161,
                                    "lng": 27.54885
                                },
                                {
                                    "lat": 47.171620000000004,
                                    "lng": 27.548820000000003
                                },
                                {
                                    "lat": 47.17163,
                                    "lng": 27.54878
                                },
                                {
                                    "lat": 47.17163,
                                    "lng": 27.547960000000003
                                },
                                {
                                    "lat": 47.171640000000004,
                                    "lng": 27.547570000000004
                                },
                                {
                                    "lat": 47.17166,
                                    "lng": 27.547240000000002
                                },
                                {
                                    "lat": 47.17168,
                                    "lng": 27.547010000000004
                                },
                                {
                                    "lat": 47.171690000000005,
                                    "lng": 27.546950000000002
                                },
                                {
                                    "lat": 47.171690000000005,
                                    "lng": 27.546930000000003
                                },
                                {
                                    "lat": 47.1717,
                                    "lng": 27.546780000000002
                                },
                                {
                                    "lat": 47.171690000000005,
                                    "lng": 27.54625
                                },
                                {
                                    "lat": 47.171670000000006,
                                    "lng": 27.546090000000003
                                }
                            ],
                            "lat_lngs": [
                                {
                                    "lat": 47.1704,
                                    "lng": 27.549760000000003
                                },
                                {
                                    "lat": 47.17083,
                                    "lng": 27.549460000000003
                                },
                                {
                                    "lat": 47.17089000000001,
                                    "lng": 27.54942
                                },
                                {
                                    "lat": 47.17152,
                                    "lng": 27.548980000000004
                                },
                                {
                                    "lat": 47.17156000000001,
                                    "lng": 27.548930000000002
                                },
                                {
                                    "lat": 47.17159,
                                    "lng": 27.548890000000004
                                },
                                {
                                    "lat": 47.171600000000005,
                                    "lng": 27.54887
                                },
                                {
                                    "lat": 47.17161,
                                    "lng": 27.54885
                                },
                                {
                                    "lat": 47.171620000000004,
                                    "lng": 27.548820000000003
                                },
                                {
                                    "lat": 47.17163,
                                    "lng": 27.54878
                                },
                                {
                                    "lat": 47.17163,
                                    "lng": 27.547960000000003
                                },
                                {
                                    "lat": 47.171640000000004,
                                    "lng": 27.547570000000004
                                },
                                {
                                    "lat": 47.17166,
                                    "lng": 27.547240000000002
                                },
                                {
                                    "lat": 47.17168,
                                    "lng": 27.547010000000004
                                },
                                {
                                    "lat": 47.171690000000005,
                                    "lng": 27.546950000000002
                                },
                                {
                                    "lat": 47.171690000000005,
                                    "lng": 27.546930000000003
                                },
                                {
                                    "lat": 47.1717,
                                    "lng": 27.546780000000002
                                },
                                {
                                    "lat": 47.171690000000005,
                                    "lng": 27.54625
                                },
                                {
                                    "lat": 47.171670000000006,
                                    "lng": 27.546090000000003
                                }
                            ],
                            "instructions": "Mergi drept \u00eenainte",
                            "start_point": {
                                "lat": 47.170401,
                                "lng": 27.5497588
                            },
                            "end_point": {
                                "lat": 47.1716746,
                                "lng": 27.5460916
                            }
                        },
                        {
                            "distance": {
                                "text": "0,2 km",
                                "value": 183
                            },
                            "duration": {
                                "text": "1 min",
                                "value": 73
                            },
                            "end_location": {
                                "lat": 47.1733217,
                                "lng": 27.5460946
                            },
                            "maneuver": "turn-right",
                            "polyline": {
                                "points": "}e|~GabcgD]AI?g@?s@Ae@?cA?_@?g@@S@"
                            },
                            "start_location": {
                                "lat": 47.1716746,
                                "lng": 27.5460916
                            },
                            "travel_mode": "DRIVING",
                            "encoded_lat_lngs": "}e|~GabcgD]AI?g@?s@Ae@?cA?_@?g@@S@",
                            "path": [
                                {
                                    "lat": 47.171670000000006,
                                    "lng": 27.546090000000003
                                },
                                {
                                    "lat": 47.171820000000004,
                                    "lng": 27.546100000000003
                                },
                                {
                                    "lat": 47.171870000000006,
                                    "lng": 27.546100000000003
                                },
                                {
                                    "lat": 47.172070000000005,
                                    "lng": 27.546100000000003
                                },
                                {
                                    "lat": 47.17233,
                                    "lng": 27.546110000000002
                                },
                                {
                                    "lat": 47.172520000000006,
                                    "lng": 27.546110000000002
                                },
                                {
                                    "lat": 47.17286000000001,
                                    "lng": 27.546110000000002
                                },
                                {
                                    "lat": 47.17302,
                                    "lng": 27.546110000000002
                                },
                                {
                                    "lat": 47.17322,
                                    "lng": 27.546100000000003
                                },
                                {
                                    "lat": 47.173320000000004,
                                    "lng": 27.546090000000003
                                }
                            ],
                            "lat_lngs": [
                                {
                                    "lat": 47.171670000000006,
                                    "lng": 27.546090000000003
                                },
                                {
                                    "lat": 47.171820000000004,
                                    "lng": 27.546100000000003
                                },
                                {
                                    "lat": 47.171870000000006,
                                    "lng": 27.546100000000003
                                },
                                {
                                    "lat": 47.172070000000005,
                                    "lng": 27.546100000000003
                                },
                                {
                                    "lat": 47.17233,
                                    "lng": 27.546110000000002
                                },
                                {
                                    "lat": 47.172520000000006,
                                    "lng": 27.546110000000002
                                },
                                {
                                    "lat": 47.17286000000001,
                                    "lng": 27.546110000000002
                                },
                                {
                                    "lat": 47.17302,
                                    "lng": 27.546110000000002
                                },
                                {
                                    "lat": 47.17322,
                                    "lng": 27.546100000000003
                                },
                                {
                                    "lat": 47.173320000000004,
                                    "lng": 27.546090000000003
                                }
                            ],
                            "instructions": "Vireaz\u0103 <b>la dreapta</b> pe <b>Strada Sergent Grigore Ioan</b>",
                            "start_point": {
                                "lat": 47.1716746,
                                "lng": 27.5460916
                            },
                            "end_point": {
                                "lat": 47.1733217,
                                "lng": 27.5460946
                            }
                        },
                        {
                            "distance": {
                                "text": "0,7 km",
                                "value": 660
                            },
                            "duration": {
                                "text": "2 min",
                                "value": 99
                            },
                            "end_location": {
                                "lat": 47.1727005,
                                "lng": 27.5374346
                            },
                            "maneuver": "turn-left",
                            "polyline": {
                                "points": "gp|~GabcgDHtD?TDlBN`GDrBH`DBd@VbGDtA?B@l@@\\?D@zABhDDf@@NFZN`A"
                            },
                            "start_location": {
                                "lat": 47.1733217,
                                "lng": 27.5460946
                            },
                            "travel_mode": "DRIVING",
                            "encoded_lat_lngs": "gp|~GabcgDHtD?TDlBN`GDrBH`DBd@VbGDtA?B@l@@\\?D@zABhDDf@@NFZN`A",
                            "path": [
                                {
                                    "lat": 47.173320000000004,
                                    "lng": 27.546090000000003
                                },
                                {
                                    "lat": 47.17327,
                                    "lng": 27.545180000000002
                                },
                                {
                                    "lat": 47.17327,
                                    "lng": 27.545070000000003
                                },
                                {
                                    "lat": 47.17324000000001,
                                    "lng": 27.544520000000002
                                },
                                {
                                    "lat": 47.17316,
                                    "lng": 27.54323
                                },
                                {
                                    "lat": 47.17313,
                                    "lng": 27.542650000000002
                                },
                                {
                                    "lat": 47.173080000000006,
                                    "lng": 27.54184
                                },
                                {
                                    "lat": 47.17306000000001,
                                    "lng": 27.54165
                                },
                                {
                                    "lat": 47.172940000000004,
                                    "lng": 27.540350000000004
                                },
                                {
                                    "lat": 47.17291,
                                    "lng": 27.539920000000002
                                },
                                {
                                    "lat": 47.17291,
                                    "lng": 27.539900000000003
                                },
                                {
                                    "lat": 47.172900000000006,
                                    "lng": 27.53967
                                },
                                {
                                    "lat": 47.17289,
                                    "lng": 27.539520000000003
                                },
                                {
                                    "lat": 47.17289,
                                    "lng": 27.53949
                                },
                                {
                                    "lat": 47.172880000000006,
                                    "lng": 27.539030000000004
                                },
                                {
                                    "lat": 47.17286000000001,
                                    "lng": 27.53818
                                },
                                {
                                    "lat": 47.172830000000005,
                                    "lng": 27.53798
                                },
                                {
                                    "lat": 47.17282,
                                    "lng": 27.5379
                                },
                                {
                                    "lat": 47.17278,
                                    "lng": 27.537760000000002
                                },
                                {
                                    "lat": 47.172700000000006,
                                    "lng": 27.53743
                                }
                            ],
                            "lat_lngs": [
                                {
                                    "lat": 47.173320000000004,
                                    "lng": 27.546090000000003
                                },
                                {
                                    "lat": 47.17327,
                                    "lng": 27.545180000000002
                                },
                                {
                                    "lat": 47.17327,
                                    "lng": 27.545070000000003
                                },
                                {
                                    "lat": 47.17324000000001,
                                    "lng": 27.544520000000002
                                },
                                {
                                    "lat": 47.17316,
                                    "lng": 27.54323
                                },
                                {
                                    "lat": 47.17313,
                                    "lng": 27.542650000000002
                                },
                                {
                                    "lat": 47.173080000000006,
                                    "lng": 27.54184
                                },
                                {
                                    "lat": 47.17306000000001,
                                    "lng": 27.54165
                                },
                                {
                                    "lat": 47.172940000000004,
                                    "lng": 27.540350000000004
                                },
                                {
                                    "lat": 47.17291,
                                    "lng": 27.539920000000002
                                },
                                {
                                    "lat": 47.17291,
                                    "lng": 27.539900000000003
                                },
                                {
                                    "lat": 47.172900000000006,
                                    "lng": 27.53967
                                },
                                {
                                    "lat": 47.17289,
                                    "lng": 27.539520000000003
                                },
                                {
                                    "lat": 47.17289,
                                    "lng": 27.53949
                                },
                                {
                                    "lat": 47.172880000000006,
                                    "lng": 27.539030000000004
                                },
                                {
                                    "lat": 47.17286000000001,
                                    "lng": 27.53818
                                },
                                {
                                    "lat": 47.172830000000005,
                                    "lng": 27.53798
                                },
                                {
                                    "lat": 47.17282,
                                    "lng": 27.5379
                                },
                                {
                                    "lat": 47.17278,
                                    "lng": 27.537760000000002
                                },
                                {
                                    "lat": 47.172700000000006,
                                    "lng": 27.53743
                                }
                            ],
                            "instructions": "Vireaz\u0103 <b>la st\u00e2nga</b> pe <b>Strada Canta</b>/<wbr/><b>DN28</b>/<wbr/><b>E58</b>/<wbr/><b>E583</b>",
                            "start_point": {
                                "lat": 47.1733217,
                                "lng": 27.5460946
                            },
                            "end_point": {
                                "lat": 47.1727005,
                                "lng": 27.5374346
                            }
                        },
                        {
                            "distance": {
                                "text": "33 m",
                                "value": 33
                            },
                            "duration": {
                                "text": "1 min",
                                "value": 16
                            },
                            "end_location": {
                                "lat": 47.1724089,
                                "lng": 27.537439
                            },
                            "maneuver": "turn-left",
                            "polyline": {
                                "points": "kl|~G}kagDJBD@B?PAH?DC@A"
                            },
                            "start_location": {
                                "lat": 47.1727005,
                                "lng": 27.5374346
                            },
                            "travel_mode": "DRIVING",
                            "encoded_lat_lngs": "kl|~G}kagDJBD@B?PAH?DC@A",
                            "path": [
                                {
                                    "lat": 47.172700000000006,
                                    "lng": 27.53743
                                },
                                {
                                    "lat": 47.17264,
                                    "lng": 27.53741
                                },
                                {
                                    "lat": 47.172610000000006,
                                    "lng": 27.5374
                                },
                                {
                                    "lat": 47.17259000000001,
                                    "lng": 27.5374
                                },
                                {
                                    "lat": 47.17250000000001,
                                    "lng": 27.53741
                                },
                                {
                                    "lat": 47.172450000000005,
                                    "lng": 27.53741
                                },
                                {
                                    "lat": 47.17242,
                                    "lng": 27.53743
                                },
                                {
                                    "lat": 47.172410000000006,
                                    "lng": 27.537440000000004
                                }
                            ],
                            "lat_lngs": [
                                {
                                    "lat": 47.172700000000006,
                                    "lng": 27.53743
                                },
                                {
                                    "lat": 47.17264,
                                    "lng": 27.53741
                                },
                                {
                                    "lat": 47.172610000000006,
                                    "lng": 27.5374
                                },
                                {
                                    "lat": 47.17259000000001,
                                    "lng": 27.5374
                                },
                                {
                                    "lat": 47.17250000000001,
                                    "lng": 27.53741
                                },
                                {
                                    "lat": 47.172450000000005,
                                    "lng": 27.53741
                                },
                                {
                                    "lat": 47.17242,
                                    "lng": 27.53743
                                },
                                {
                                    "lat": 47.172410000000006,
                                    "lng": 27.537440000000004
                                }
                            ],
                            "instructions": "Vireaz\u0103 <b>la st\u00e2nga</b><div style=\"font-size:0.9em\">Destina\u021bia va fi pe dreapta</div>",
                            "start_point": {
                                "lat": 47.1727005,
                                "lng": 27.5374346
                            },
                            "end_point": {
                                "lat": 47.1724089,
                                "lng": 27.537439
                            }
                        }
                    ],
                    "traffic_speed_entry": [],
                    "via_waypoint": [],
                    "via_waypoints": []
                }
            ],
            "overview_polyline": "_p{~G_oegD]`@I?IDi@l@EDGHEPAHKPWdA}@zDOlAI`C@hECpFKfRa@Cs@?WBuAt@uAz@iC~AMPGTApFGnBAN?fCB^]Aq@?}DA{@BHjEd@dS`@bKDlDBhDDf@Hj@N`AJBH@ZAFE",
            "summary": "Strada Canta/DN28/E58/E583",
            "warnings": [],
            "waypoint_order": [],
            "overview_path": [
                {
                    "lat": 47.16816,
                    "lng": 27.558400000000002
                },
                {
                    "lat": 47.168310000000005,
                    "lng": 27.558230000000002
                },
                {
                    "lat": 47.16836000000001,
                    "lng": 27.558230000000002
                },
                {
                    "lat": 47.16841,
                    "lng": 27.558200000000003
                },
                {
                    "lat": 47.168620000000004,
                    "lng": 27.55797
                },
                {
                    "lat": 47.16865000000001,
                    "lng": 27.557940000000002
                },
                {
                    "lat": 47.168690000000005,
                    "lng": 27.557890000000004
                },
                {
                    "lat": 47.16872,
                    "lng": 27.557800000000004
                },
                {
                    "lat": 47.168730000000004,
                    "lng": 27.557750000000002
                },
                {
                    "lat": 47.16879,
                    "lng": 27.557660000000002
                },
                {
                    "lat": 47.168910000000004,
                    "lng": 27.55731
                },
                {
                    "lat": 47.16922,
                    "lng": 27.55637
                },
                {
                    "lat": 47.16930000000001,
                    "lng": 27.55598
                },
                {
                    "lat": 47.16935,
                    "lng": 27.55533
                },
                {
                    "lat": 47.169340000000005,
                    "lng": 27.55432
                },
                {
                    "lat": 47.169360000000005,
                    "lng": 27.553110000000004
                },
                {
                    "lat": 47.16942,
                    "lng": 27.550030000000003
                },
                {
                    "lat": 47.16959000000001,
                    "lng": 27.550050000000002
                },
                {
                    "lat": 47.169850000000004,
                    "lng": 27.550050000000002
                },
                {
                    "lat": 47.169970000000006,
                    "lng": 27.550030000000003
                },
                {
                    "lat": 47.1704,
                    "lng": 27.549760000000003
                },
                {
                    "lat": 47.17083,
                    "lng": 27.549460000000003
                },
                {
                    "lat": 47.17152,
                    "lng": 27.548980000000004
                },
                {
                    "lat": 47.17159,
                    "lng": 27.548890000000004
                },
                {
                    "lat": 47.17163,
                    "lng": 27.54878
                },
                {
                    "lat": 47.171640000000004,
                    "lng": 27.547570000000004
                },
                {
                    "lat": 47.17168,
                    "lng": 27.547010000000004
                },
                {
                    "lat": 47.171690000000005,
                    "lng": 27.546930000000003
                },
                {
                    "lat": 47.171690000000005,
                    "lng": 27.54625
                },
                {
                    "lat": 47.171670000000006,
                    "lng": 27.546090000000003
                },
                {
                    "lat": 47.171820000000004,
                    "lng": 27.546100000000003
                },
                {
                    "lat": 47.172070000000005,
                    "lng": 27.546100000000003
                },
                {
                    "lat": 47.17302,
                    "lng": 27.546110000000002
                },
                {
                    "lat": 47.173320000000004,
                    "lng": 27.546090000000003
                },
                {
                    "lat": 47.17327,
                    "lng": 27.545070000000003
                },
                {
                    "lat": 47.173080000000006,
                    "lng": 27.54184
                },
                {
                    "lat": 47.17291,
                    "lng": 27.539900000000003
                },
                {
                    "lat": 47.172880000000006,
                    "lng": 27.539030000000004
                },
                {
                    "lat": 47.17286000000001,
                    "lng": 27.53818
                },
                {
                    "lat": 47.172830000000005,
                    "lng": 27.53798
                },
                {
                    "lat": 47.17278,
                    "lng": 27.537760000000002
                },
                {
                    "lat": 47.172700000000006,
                    "lng": 27.53743
                },
                {
                    "lat": 47.17264,
                    "lng": 27.53741
                },
                {
                    "lat": 47.17259000000001,
                    "lng": 27.5374
                },
                {
                    "lat": 47.172450000000005,
                    "lng": 27.53741
                },
                {
                    "lat": 47.172410000000006,
                    "lng": 27.537440000000004
                }
            ]
        }
    ],
    "status": "OK",
    "request": {
        "origin": {
            "location": {
                "lat": 47.16815216,
                "lng": 27.5583883
            }
        },
        "destination": {
            "location": {
                "lat": 47.17238,
                "lng": 27.53737
            }
        },
        "travelMode": "DRIVING",
        "drivingOptions": {
            "departureTime": "2024-06-19T00:30:00.000Z"
        }
    },
    "start_id": "125",
    "stop_id": "51"
}